aidb/__init__.py
aidb/cli.py
aidb/db_dump_schema_json.py
aidb/db_kumquat.py
aidb/main.py
aidb/secrets.py
aidb/assets/example.txt
advanced_aidb-1.0.2.dist-info/LICENSE
advanced_aidb-1.0.2.dist-info/METADATA
advanced_aidb-1.0.2.dist-info/WHEEL
advanced_aidb-1.0.2.dist-info/entry_points.txt
advanced_aidb-1.0.2.dist-info/top_level.txt
advanced_aidb-1.0.2.dist-info/RECORD
