Metadata-Version: 2.1
Name: advanced-aidb
Version: 1.0.2
Summary: ai for your database
Home-page: https://github.com/zackees/aidb
Maintainer: Zachary Vorhies
License: BSD 3-Clause License
Keywords: template-python-cmd
Classifier: Programming Language :: Python :: 3
Requires-Python: >=3.7
License-File: LICENSE
Requires-Dist: SQLAlchemy==2.0.27
Requires-Dist: keyring
Requires-Dist: PyMySQL[ed25519,rsa]
Requires-Dist: certifi
Requires-Dist: PyYAML
Requires-Dist: advanced-askai
Requires-Dist: pymysql
